plmidi_cpp.pypy39-pp73-win_amd64.pyd
plmidi/__init__.py
plmidi/sound.py
plmidi-1.1.3.dist-info/licenses/LICENSE
plmidi-1.1.3.dist-info/METADATA
plmidi-1.1.3.dist-info/WHEEL
plmidi-1.1.3.dist-info/top_level.txt
plmidi-1.1.3.dist-info/RECORD
