Metadata-Version: 2.4
Name: plmidi
Version: 1.1.3
Summary: midi player for Python Package physicsLab
Home-page: https://github.com/GoodenoughPhysicsLab/plmidi
Author: Arendelle
Author-email: 2381642961@qq.com
License: MIT
Classifier: Programming Language :: Python :: 3
Classifier: License :: OSI Approved :: MIT License
Classifier: Natural Language :: Chinese (Simplified)
Classifier: Operating System :: OS Independent
Requires-Python: >=3.8
License-File: LICENSE
Requires-Dist: mido
Dynamic: author
Dynamic: author-email
Dynamic: classifier
Dynamic: description
Dynamic: description-content-type
Dynamic: home-page
Dynamic: license
Dynamic: license-file
Dynamic: requires-dist
Dynamic: requires-python
Dynamic: summary
